{
    "os": "Linux-6.2.0-33-generic-x86_64-with-glibc2.35",
    "python": "3.9.13",
    "heartbeatAt": "2023-09-27T16:10:25.402289",
    "startedAt": "2023-09-27T16:10:24.699505",
    "docker": null,
    "cuda": null,
    "args": [],
    "state": "running",
    "program": "/home/qcqced/\ubc14\ud0d5\ud654\uba74/GitHub/commonlit_ess/train.py",
    "codePath": "train.py",
    "git": {
        "remote": "https://github.com/qcqced123/commonlit_ess.git",
        "commit": "75475fecdc09e17fcad1a3b1fe89830540f56b39"
    },
    "email": "qcqced123@gmail.com",
    "root": "/home/qcqced/\ubc14\ud0d5\ud654\uba74/GitHub/commonlit_ess",
    "host": "qcqced-B550M-H",
    "username": "qcqced",
    "executable": "/home/qcqced/anaconda3/bin/python",
    "cpu_count": 6,
    "cpu_count_logical": 12,
    "cpu_freq": {
        "current": 3.1835,
        "min": 2200.0,
        "max": 3700.0
    },
    "cpu_freq_per_core": [
        {
            "current": 3.429,
            "min": 2200.0,
            "max": 3700.0
        },
        {
            "current": 4.197,
            "min": 2200.0,
            "max": 3700.0
        },
        {
            "current": 2.2,
            "min": 2200.0,
            "max": 3700.0
        },
        {
            "current": 2.2,
            "min": 2200.0,
            "max": 3700.0
        },
        {
            "current": 2.2,
            "min": 2200.0,
            "max": 3700.0
        },
        {
            "current": 3.875,
            "min": 2200.0,
            "max": 3700.0
        },
        {
            "current": 3.409,
            "min": 2200.0,
            "max": 3700.0
        },
        {
            "current": 3.7,
            "min": 2200.0,
            "max": 3700.0
        },
        {
            "current": 2.961,
            "min": 2200.0,
            "max": 3700.0
        },
        {
            "current": 3.364,
            "min": 2200.0,
            "max": 3700.0
        },
        {
            "current": 3.079,
            "min": 2200.0,
            "max": 3700.0
        },
        {
            "current": 3.588,
            "min": 2200.0,
            "max": 3700.0
        }
    ],
    "disk": {
        "total": 680.4048233032227,
        "used": 123.59367752075195
    },
    "gpu": "NVIDIA GeForce RTX 3090",
    "gpu_count": 1,
    "gpu_devices": [
        {
            "name": "NVIDIA GeForce RTX 3090",
            "memory_total": 25769803776
        }
    ],
    "memory": {
        "total": 23.361499786376953
    }
}
